odoo/addons/helpdesk_timesheet_time_type/README.rst
odoo/addons/helpdesk_timesheet_time_type/__init__.py
odoo/addons/helpdesk_timesheet_time_type/__manifest__.py
odoo/addons/helpdesk_timesheet_time_type/i18n/helpdesk_timesheet_time_type.pot
odoo/addons/helpdesk_timesheet_time_type/i18n/it.po
odoo/addons/helpdesk_timesheet_time_type/readme/CONTRIBUTORS.md
odoo/addons/helpdesk_timesheet_time_type/readme/DESCRIPTION.md
odoo/addons/helpdesk_timesheet_time_type/static/description/icon.png
odoo/addons/helpdesk_timesheet_time_type/static/description/icon.svg
odoo/addons/helpdesk_timesheet_time_type/static/description/index.html
odoo/addons/helpdesk_timesheet_time_type/views/helpdesk_ticket_view.xml
odoo_addon_helpdesk_timesheet_time_type-18.0.1.0.0.2.dist-info/METADATA
odoo_addon_helpdesk_timesheet_time_type-18.0.1.0.0.2.dist-info/WHEEL
odoo_addon_helpdesk_timesheet_time_type-18.0.1.0.0.2.dist-info/top_level.txt
odoo_addon_helpdesk_timesheet_time_type-18.0.1.0.0.2.dist-info/RECORD
